Metadata-Version: 2.1
Name: monoclparse
Version: 0.0.1
Summary: Parse Monocl Excel business report documents and intersect them!
Home-page: https://github.com/clintval/monoclparse
Author: clintval
Author-email: valentine.clint@gmail.com
License: MIT
Download-URL: https://github.com/clintval/monoclparse/archive/v0.0.1.tar.gz
Project-URL: Documentation, https://monoclparse.readthedocs.io
Project-URL: Issue Tracker, https://github.com/clintval/monoclparse/issues
Keywords: monocl business report
Platform: UNKNOWN
Classifier: Development Status :: 2 - Pre-Alpha
Classifier: Intended Audience :: Developers
Classifier: License :: OSI Approved :: MIT License
Classifier: Programming Language :: Python :: 3.6
Classifier: Programming Language :: Python :: 3.7
